perfplot/__about__.py
perfplot/__init__.py
perfplot/_exceptions.py
perfplot/_main.py
perfplot-0.11.1.dist-info/METADATA
perfplot-0.11.1.dist-info/WHEEL
perfplot-0.11.1.dist-info/top_level.txt
perfplot-0.11.1.dist-info/RECORD
