Metadata-Version: 2.1
Name: perfplot
Version: 0.11.1
Summary: Performance plots for Python code snippets
Author-email: Nico Schlömer <nico.schloemer@gmail.com>
Keywords: performance,profile
Classifier: Development Status :: 5 - Production/Stable
Classifier: Intended Audience :: Developers
Classifier: License :: Other/Proprietary License
Classifier: Operating System :: OS Independent
Classifier: Programming Language :: Python
Classifier: Programming Language :: Python :: 3
Classifier: Programming Language :: Python :: 3.7
Classifier: Programming Language :: Python :: 3.8
Classifier: Programming Language :: Python :: 3.9
Classifier: Programming Language :: Python :: 3.10
Classifier: Topic :: Software Development
Classifier: Topic :: Utilities
Requires-Python: >=3.7
Requires-Dist: x21 (>=0.4.1,<0.5.0)
Requires-Dist: matplotlib
Requires-Dist: matplotx
Requires-Dist: numpy
Requires-Dist: rich
